OpenstackZuizhongYonghuwendangJiantizhongwenban/README.md
OpenstackZuizhongYonghuwendangJiantizhongwenban/__init__.py
OpenstackZuizhongYonghuwendangJiantizhongwenban/__main__.py
OpenstackZuizhongYonghuwendangJiantizhongwenban/file.epub
OpenstackZuizhongYonghuwendangJiantizhongwenban/index.html
OpenstackZuizhongYonghuwendangJiantizhongwenban/css/__init__.py
OpenstackZuizhongYonghuwendangJiantizhongwenban/css/annotations.css
OpenstackZuizhongYonghuwendangJiantizhongwenban/css/main.css
OpenstackZuizhongYonghuwendangJiantizhongwenban/css/normalize.css
OpenstackZuizhongYonghuwendangJiantizhongwenban/css/popup.css
OpenstackZuizhongYonghuwendangJiantizhongwenban/font/__init__.py
OpenstackZuizhongYonghuwendangJiantizhongwenban/font/fontello.eot
OpenstackZuizhongYonghuwendangJiantizhongwenban/font/fontello.svg
OpenstackZuizhongYonghuwendangJiantizhongwenban/font/fontello.ttf
OpenstackZuizhongYonghuwendangJiantizhongwenban/font/fontello.woff
OpenstackZuizhongYonghuwendangJiantizhongwenban/img/__init__.py
OpenstackZuizhongYonghuwendangJiantizhongwenban/img/annotator-glyph-sprite.png
OpenstackZuizhongYonghuwendangJiantizhongwenban/img/annotator-icon-sprite.png
OpenstackZuizhongYonghuwendangJiantizhongwenban/img/apple-touch-icon.png
OpenstackZuizhongYonghuwendangJiantizhongwenban/img/cancelfullscreen.png
OpenstackZuizhongYonghuwendangJiantizhongwenban/img/close.png
OpenstackZuizhongYonghuwendangJiantizhongwenban/img/fullscreen.png
OpenstackZuizhongYonghuwendangJiantizhongwenban/img/loader.gif
OpenstackZuizhongYonghuwendangJiantizhongwenban/img/menu-icon.png
OpenstackZuizhongYonghuwendangJiantizhongwenban/img/save.png
OpenstackZuizhongYonghuwendangJiantizhongwenban/img/saved.png
OpenstackZuizhongYonghuwendangJiantizhongwenban/img/settings-s.png
OpenstackZuizhongYonghuwendangJiantizhongwenban/img/settings.png
OpenstackZuizhongYonghuwendangJiantizhongwenban/img/star.png
OpenstackZuizhongYonghuwendangJiantizhongwenban/js/__init__.py
openstack_zuizhong_yonghuwendang_jiantizhongwenban-2024.3.3.0.dist-info/METADATA
openstack_zuizhong_yonghuwendang_jiantizhongwenban-2024.3.3.0.dist-info/WHEEL
openstack_zuizhong_yonghuwendang_jiantizhongwenban-2024.3.3.0.dist-info/entry_points.txt
openstack_zuizhong_yonghuwendang_jiantizhongwenban-2024.3.3.0.dist-info/top_level.txt
openstack_zuizhong_yonghuwendang_jiantizhongwenban-2024.3.3.0.dist-info/RECORD
